m2c/__init__.py
m2c/apimodel.py
m2c/apimodel_v4.py
m2c/build.py
m2c/cmdmodel.py
m2c/conf.py
m2c/helper.py
m2c/m2c.py
m2c/objmodel.py
m2c/objtpl.py
m2c/schema.py
m2c/service.py
m2c/swagger.py
m2c/swagger3.py
m2c/version.py
m2c/watchgo.py
m2c-0.4.7.data/scripts/m2c
m2c-0.4.7.dist-info/METADATA
m2c-0.4.7.dist-info/WHEEL
m2c-0.4.7.dist-info/top_level.txt
m2c-0.4.7.dist-info/RECORD
