Metadata-Version: 2.1
Name: m2c
Version: 0.4.7
Summary: m2c
Home-page: https://github.com/yangbinnnn/m2c
Author: yangbinnnn
Author-email: yangbinnnn@gmail.com
License: UNKNOWN
Platform: UNKNOWN
Classifier: Programming Language :: Python :: 2.7
Classifier: Programming Language :: Python :: 3
Classifier: License :: OSI Approved :: MIT License
Classifier: Operating System :: OS Independent
Requires-Dist: pyyaml
Requires-Dist: psutil
Requires-Dist: watchdog
